spine/.DS_Store
spine/__init__.py
spine/cli.py
spine/main.py
spine/chains/README.md
spine/chains/__init__.py
spine/indexes/README.md
spine/indexes/__init__.py
spine/memory/README.md
spine/memory/__init__.py
spine/prompts/__init__.py
spine/tools/document_loaders.py
spine/utils/.DS_Store
spine/utils/README.md
spine/utils/__init__.py
spine/utils/azure_utils.py
spine/utils/env_utils.py
spine/utils/misc/__init__.py
spine/utils/misc/logging_utils.py
spine/utils/misc/misc_utils.py
spine_ai-0.0.2.dist-info/LICENSE
spine_ai-0.0.2.dist-info/METADATA
spine_ai-0.0.2.dist-info/WHEEL
spine_ai-0.0.2.dist-info/entry_points.txt
spine_ai-0.0.2.dist-info/top_level.txt
spine_ai-0.0.2.dist-info/RECORD
